render_engine_tailwindcss/__init__.py
render_engine_tailwindcss/plugins.py
render_engine_tailwindcss-2023.10.2.dist-info/LICENSE
render_engine_tailwindcss-2023.10.2.dist-info/METADATA
render_engine_tailwindcss-2023.10.2.dist-info/WHEEL
render_engine_tailwindcss-2023.10.2.dist-info/top_level.txt
render_engine_tailwindcss-2023.10.2.dist-info/RECORD
