Metadata-Version: 2.1
Name: render-engine-tailwindcss
Version: 2023.10.2
Summary: tailwindcss-parser for Render Engine
Project-URL: homepage, https://github.com/kjaymiller/render_engine_tailwindcss/
Project-URL: repository, https://github.com/kjaymiller/render_engine_tailwindcss/
License-File: LICENSE
Requires-Dist: render-engine >=2023.10.3a5
Requires-Dist: pytailwindcss
Provides-Extra: dev
Requires-Dist: pytest ; extra == 'dev'
